sql_runner/__init__.py
sql_runner/deps.py
sql_runner/parsing.py
sql_runner/query_list.py
sql_runner/run_sql.py
sql_runner/runner.py
sql_runner/tests.py
sql_runner/db/__init__.py
sql_runner/db/azuredwh.py
sql_runner/db/bigquery.py
sql_runner/db/postgres.py
sql_runner/db/redshift.py
sql_runner/db/snowflake.py
sql_runner-0.5.0.dist-info/LICENSE
sql_runner-0.5.0.dist-info/METADATA
sql_runner-0.5.0.dist-info/WHEEL
sql_runner-0.5.0.dist-info/entry_points.txt
sql_runner-0.5.0.dist-info/top_level.txt
sql_runner-0.5.0.dist-info/RECORD
