Metadata-Version: 2.1
Name: sql-runner
Version: 0.5.0
Summary: DEPT SQL runner
Home-page: UNKNOWN
Author: sql-runner contributors
License: Apache 2.0
Platform: UNKNOWN
Requires-Python: ~=3.8
Requires-Dist: networkx (==2.5)
Requires-Dist: pydot (==1.4.2)
Requires-Dist: graphviz (==0.16)
Requires-Dist: pythondialog
Requires-Dist: sqlparse
Provides-Extra: azuredwh
Requires-Dist: pyodbc ; extra == 'azuredwh'
Provides-Extra: bigquery
Requires-Dist: google-cloud-bigquery (==2.12.0) ; extra == 'bigquery'
Provides-Extra: postgres
Requires-Dist: psycopg2-binary ; extra == 'postgres'
Provides-Extra: redshift
Requires-Dist: psycopg2-binary ; extra == 'redshift'
Provides-Extra: s3
Requires-Dist: boto3 (==1.17.33) ; extra == 's3'
Provides-Extra: snowflake
Requires-Dist: snowflake-connector-python (==2.4.1) ; extra == 'snowflake'
